{
  "product_id": "pimprod2037385",
  "product_url": "https://www.ulta.com/p/8h-matte-comfort-lipliner-pimprod2037385",
  "extracted_at": "2025-09-23T03:10:04.589495+00:00",
  "product_name": "Essence8H Matte Comfort Lipliner",
  "brand": "Essence",
  "categories": [
    "Home",
    "Makeup",
    "Lips",
    "Lip Liner"
  ],
  "category_keys": [
    "home",
    "makeup",
    "lips",
    "lip-liner"
  ],
  "currency": "USD",
  "list_price": "",
  "sale_price": "3.99",
  "availability": "in_stock",
  "rating_avg": "4.2",
  "rating_count": "93",
  "images": [
    "https://media.ulta.com/i/ulta/2603068?w=500&h=500"
  ],
  "detailed_images": [
    "https://media.ulta.com/i/ulta/2603068?w=600&h=600&fmt=auto",
    "https://media.ulta.com/i/ulta/2603068_sm?w=600&h=600&fmt=auto",
    "https://media.ulta.com/i/ulta/2603068_alt01?w=600&h=600&fmt=auto",
    "https://media.ulta.com/i/ulta/2603068_alt02?w=600&h=600&fmt=auto",
    "https://media.ulta.com/i/ulta/2603068_alt03?w=600&h=600&fmt=auto",
    "https://media.ulta.com/i/ulta/2603068_alt04?w=600&h=600&fmt=auto",
    "https://media.ulta.com/i/ulta/2603065cm_alt01?w=600&h=600&fmt=auto"
  ],
  "summary": "SummaryHighlightsClean IngredientsCruelty FreeVeganGive BackFor a long-lasting lip color that won't quit, choose essence 8H Matte Comfort Lip Liner!",
  "details": "DetailsFeaturesLong-wearing formula glides on smoothlyFull coverage formulaWaterproof formulaThe lightweight formula helps to keep lips feeling comfortable throughout the dayContains an exclusive sharpener on the bottom of its cap for easy applicationFormulated WithoutAnimal by-productsGlutenParabensPreservativesAlcoholMicroplastic particlesItem 2603068How To UseOutline lips with 8H Matte Comfort Lipliner. Closely following the contour, apply a corresponding shade of your favorite essence lipstick. For a glossier finish, apply your favorite essence lip-gloss. For a semi-matte finish, apply liner alone over the entire lip.IngredientsMethyl Trimethicone, Oryza Sativa (Rice) Bran Wax, Trimethylsiloxysilicate, Octyldodecanol, Synthetic Fluorphlogopite, Acrylates/Dimethicone Copolymer, Persea Gratissima (Avocado) Oil, Tocopheryl Acetate, Disteardimonium Hectorite, Pentaerythrityl Tetra-Di-T-Butyl Hydroxyhydrocinnamate, Propylene Carbonate, Parfum (Fragrance), CI 77491, CI 77492, CI 77499 (Iron Oxides), CI 77891 (Titanium Dioxide).",
  "how_to_use": "Outline lips with 8H Matte Comfort Lipliner. Closely following the contour, apply a corresponding shade of your favorite essence lipstick. For a glossier finish, apply your favorite essence lip-gloss. For a semi-matte finish, apply liner alone over the entire lip.",
  "ingredients": [
    "Methyl Trimethicone",
    "Oryza Sativa (Rice) Bran Wax",
    "Trimethylsiloxysilicate",
    "Octyldodecanol",
    "Synthetic Fluorphlogopite",
    "Acrylates/Dimethicone Copolymer",
    "Persea Gratissima (Avocado) Oil",
    "Tocopheryl Acetate",
    "Disteardimonium Hectorite",
    "Pentaerythrityl Tetra-Di-T-Butyl Hydroxyhydrocinnamate",
    "Propylene Carbonate",
    "Parfum (Fragrance)"
  ],
  "extended_contents": {},
  "tags": {
    "category": [
      "makeup",
      "lips",
      "lip",
      "cosmetics"
    ],
    "product_type": [
      "serum",
      "lip liner",
      "eyeliner"
    ],
    "skin_type": [
      "oily"
    ],
    "finish": [
      "matte",
      "satin",
      "sheer",
      "full coverage",
      "long-wear",
      "waterproof",
      "creamy",
      "oil"
    ],
    "ingredients": [
      "synthetic",
      "fragrance"
    ],
    "brand": [
      "mid-range",
      "budget"
    ],
    "special_features": [
      "cruelty-free",
      "vegan"
    ]
  },
  "reviews": {
    "product_id": "pimprod2037385",
    "total_reviews": 93,
    "reviews": [
      {
        "review_id": 561009786,
        "rating": 5,
        "headline": "I would buy it again",
        "comments": "Love",
        "nickname": "Debbie",
        "location": "Alabama",
        "created_date": 1755962355763,
        "bottom_line": "Yes",
        "helpful_votes": 0,
        "not_helpful_votes": 0
      },
      {
        "review_id": 559158259,
        "rating": 5,
        "headline": "Love the brand",
        "comments": "Nice color and love the brand",
        "nickname": "",
        "location": "Hemet, ca",
        "created_date": 1754126837556,
        "bottom_line": "Yes",
        "helpful_votes": 0,
        "not_helpful_votes": 0
      },
      {
        "review_id": 556722118,
        "rating": 5,
        "headline": "Great liner",
        "comments": "Great shade, great product",
        "nickname": "Sylvia L",
        "location": "Corpus Christi, TX",
        "created_date": 1751819987657,
        "bottom_line": "Yes",
        "helpful_votes": 0,
        "not_helpful_votes": 0
      },
      {
        "review_id": 556722134,
        "rating": 5,
        "headline": "Great liner",
        "comments": "Awesome",
        "nickname": "Sylvia L",
        "location": "Corpus Christi, TX",
        "created_date": 1751819931550,
        "bottom_line": "Yes",
        "helpful_votes": 0,
        "not_helpful_votes": 0
      },
      {
        "review_id": 556722059,
        "rating": 5,
        "headline": "Great product",
        "comments": "Great shade and creaminess for the awesome price",
        "nickname": "Sylvia L",
        "location": "Corpus Christi, TX",
        "created_date": 1751819810464,
        "bottom_line": "Yes",
        "helpful_votes": 1,
        "not_helpful_votes": 0
      },
      {
        "review_id": 555784128,
        "rating": 3,
        "headline": "Not my style",
        "comments": "Usually I don't buy lip products because I'm just not that good at doing a lip liner I tried it just not the color I was expecting I thought it would of been darker but the color is off for my skin tone but smooth application just not a color match for me",
        "nickname": "Jessica",
        "location": "Florida",
        "created_date": 1750720629725,
        "bottom_line": "Yes",
        "helpful_votes": 0,
        "not_helpful_votes": 2
      },
      {
        "review_id": 554592569,
        "rating": 4,
        "headline": "05 Pink Blush",
        "comments": "Smooth, creamy, easy to apply (no tugging), long lasting! Pink Blush is a bright pink that pairs well with pink and rose color lipsticks. This is a beautiful color of lipliner at a beautiful (low) price!",
        "nickname": "Susan",
        "location": "Illinois",
        "created_date": 1749154853122,
        "bottom_line": null,
        "helpful_votes": 4,
        "not_helpful_votes": 0
      },
      {
        "review_id": 554408547,
        "rating": 5,
        "headline": "Very affordable",
        "comments": "Goes on really nice and soft",
        "nickname": "Drea",
        "location": "Stockton",
        "created_date": 1748890949677,
        "bottom_line": null,
        "helpful_votes": 2,
        "not_helpful_votes": 0
      },
      {
        "review_id": 552763592,
        "rating": 3,
        "headline": "Color seems off from product photo",
        "comments": "The formula seems to glide on real smooth. But the color i thought id be getting doesnt match. I did an order pickup and when i got home to try this it looks more of a light brown nude. Im a brown girl and i despise the look having a nude color on my lips, it just doesnt go with my complexion, IMO. Definitely willing to try other colors though, i think this product has potential.",
        "nickname": "Jazzy",
        "location": "Austin, TX",
        "created_date": 1746199896585,
        "bottom_line": null,
        "helpful_votes": 3,
        "not_helpful_votes": 1
      },
      {
        "review_id": 552177645,
        "rating": 5,
        "headline": "Best lip liner",
        "comments": "Best lip liner. Great colour, great staying power",
        "nickname": "Ters",
        "location": "Wisconsin",
        "created_date": 1745346343472,
        "bottom_line": "Yes",
        "helpful_votes": 3,
        "not_helpful_votes": 0
      },
      {
        "review_id": 550985727,
        "rating": 5,
        "headline": "One of the Best Liners!",
        "comments": "Cinnamon spice is the perfect medium nude shade. It glides on so smoothly, doesn't break, and it lasts all day (8+ hrs) through eating and exercising! I am so impressed! It's just as good as the Urban Decay waterproof lip liners.",
        "nickname": "SCVa",
        "location": "Virginia",
        "created_date": 1743727677774,
        "bottom_line": null,
        "helpful_votes": 1,
        "not_helpful_votes": 0
      },
      {
        "review_id": 548835974,
        "rating": 5,
        "headline": "Best lip liner",
        "comments": "I buy this on repeat! So inexpensive and long lasting!",
        "nickname": "Tera",
        "location": "Madison",
        "created_date": 1742056222689,
        "bottom_line": "Yes",
        "helpful_votes": 1,
        "not_helpful_votes": 0
      },
      {
        "review_id": 546091516,
        "rating": 4,
        "headline": "I'm Satisfied",
        "comments": "It's not my favorite but I like it. It had a built in sharpener at the end so it's convienient. The color is cute and matte. It stays on for awhile but it's not long-lasting.",
        "nickname": "Mari R.",
        "location": "San Bernardino, CA",
        "created_date": 1739000925483,
        "bottom_line": null,
        "helpful_votes": 5,
        "not_helpful_votes": 4
      },
      {
        "review_id": 545968322,
        "rating": 5,
        "headline": "Holy grail!",
        "comments": "I love this lipliner and how long it lasts on. I wear it for work 10+ hours and just have to reapply once! Love how it's retractable also, so you dont really have to waste product sharpening (there is a built in sharpener though). I'll always repurchase!!",
        "nickname": "Lbphxx",
        "location": "Arizona",
        "created_date": 1738822351513,
        "bottom_line": null,
        "helpful_votes": 3,
        "not_helpful_votes": 0
      },
      {
        "review_id": 545824312,
        "rating": 5,
        "headline": "I would buy this again .",
        "comments": "I got very pale skin so just being able to find a shade of lip liner that looks good on me and is the color that I like is great .",
        "nickname": "brie",
        "location": "North Carolina",
        "created_date": 1738514165546,
        "bottom_line": "Yes",
        "helpful_votes": 1,
        "not_helpful_votes": 0
      },
      {
        "review_id": 543660533,
        "rating": 5,
        "headline": "super great and affordable lip liner",
        "comments": "this lip liner is so pretty and it comes with a sharpener that works great! it's so affordable and looks very seamless and blends out easy while also being smudge free and water proof. I would definitely recommend.",
        "nickname": "clara",
        "location": "Michigan City, Indiana,USA",
        "created_date": 1737411452311,
        "bottom_line": "Yes",
        "helpful_votes": 1,
        "not_helpful_votes": 0
      },
      {
        "review_id": 542269549,
        "rating": 5,
        "headline": "Nice shade and easy to apply",
        "comments": "Great color, easy to apply!",
        "nickname": "Becky",
        "location": "MD",
        "created_date": 1736095215059,
        "bottom_line": "Yes",
        "helpful_votes": 1,
        "not_helpful_votes": 1
      },
      {
        "review_id": 542268727,
        "rating": 5,
        "headline": "I buy the sun repeat now that I have tried it",
        "comments": "One of the best liners I have ever used aside from some of the NYX ones.",
        "nickname": "Tera",
        "location": "Madison, Wisconsin",
        "created_date": 1736093531849,
        "bottom_line": "Yes",
        "helpful_votes": 0,
        "not_helpful_votes": 1
      },
      {
        "review_id": 542212349,
        "rating": 5,
        "headline": "Amazing for beginners",
        "comments": "I really enjoyed using this pencil as a beginner trying to use make up. Affordable and got the job done. The only con I would have to say is that it does transfer, but it's worth it for the price.",
        "nickname": "777Lizz333",
        "location": "st.louis",
        "created_date": 1735969039099,
        "bottom_line": null,
        "helpful_votes": 2,
        "not_helpful_votes": 1
      },
      {
        "review_id": 539181855,
        "rating": 3,
        "headline": "Online Color Not Accurate",
        "comments": "Colors are much lighter in person. I thought I was getting a true brown color, but instead a light nude. Pretty nude, but a bit too light for me and not enough contrast.  For the price, this is really good and would be gorgeous on someone with fairer skin.",
        "nickname": "Sc80",
        "location": "Virginia",
        "created_date": 1733612987328,
        "bottom_line": null,
        "helpful_votes": 4,
        "not_helpful_votes": 1
      }
    ],
    "paging": {
      "total_results": 81,
      "pages_total": 5,
      "page_size": 20,
      "current_page_number": 1,
      "next_page_url": "/m/6406/l/en_US/product/pimprod2037385/reviews?paging.from=20&paging.size=20&filters=&search=&sort=Newest&image_only=false&page_locale=en_US&native_only=true"
    },
    "rollup": {
      "properties": [],
      "rating_histogram": [
        5,
        7,
        9,
        16,
        56
      ],
      "review_histogram": [
        5,
        7,
        9,
        16,
        56
      ],
      "rating_count": 93,
      "review_count": 93,
      "average_rating": 4.19,
      "recommended_ratio": 0.93,
      "media": [
        {
          "id": "463660515",
          "review_id": 463660477,
          "uri": "//res.cloudinary.com/powerreviews/image/upload/f_auto,q_auto,h_768,w_auto/d_portal-no-product-image_ttlfpi.svg/prod/cgeclmrbjquztcuyjcwd.jpg",
          "headline": "Beautiful soft brown shade",
          "rating": 5,
          "helpful_votes": 0,
          "not_helpful_votes": 0,
          "type": "image",
          "caption": "Cinnamon spice",
          "nickname": "Kenia",
          "created_date": 1688829088514
        },
        {
          "id": "453717886",
          "review_id": 453717941,
          "uri": "//res.cloudinary.com/powerreviews/image/upload/f_auto,q_auto,h_768,w_auto/d_portal-no-product-image_ttlfpi.svg/prod/hgtqhiqebxjsjzccckyp.jpg",
          "headline": "Best liner at a great price",
          "rating": 5,
          "helpful_votes": 0,
          "not_helpful_votes": 0,
          "type": "image",
          "nickname": "Melissa",
          "created_date": 1681874509348
        }
      ],
      "faceoff_positive": {
        "comments": "I tried the rosey brown as a liner and it stayed put. The color is so nice I filled in my lips and it made a long lasting matte winter color. Going to Try 2-3 more shades!",
        "headline": "8 hr matte lip liner",
        "rating": 4,
        "ugc_id": 515155251
      },
      "faceoff_negative": {
        "comments": "I loved the old 8h fragrance free waterproof lip liner so much! It has been discontinued and I'm so sad. This seemed similar, I believe it is the new version and although I like the colors, I absolutely hate the smell. Why add fragrance in a lip liner! But this doesn't even smell like a nice fragrance, it smells horrible and it tastes bad too. ;((( please bring back the old formula or at least remove the fragrance on this one!!! Please!!!",
        "headline": "Liked the other 8h lip liner more, why discontinue",
        "rating": 3,
        "ugc_id": 515155194
      },
      "native_review_count": 81,
      "native_sampling_review_count": 0,
      "native_sweepstakes_review_count": 0,
      "native_community_content_review_count": 0,
      "syndicated_review_count": 12,
      "locale": "en_US"
    }
  }
}